[
    {
        "이름": "이가연",
        "생년월일": "1999-10-29",
        "날짜": "2024-08-29",
        "b-actin": 29.7231,
        "TIMP3": 53.8887,
        "COL10A1": 58.4912,
        "FLG": 32.2975,
        "AQP3": 31.64111
    },
    {
        "이름": "김소영",
        "생년월일": "1995-08-01",
        "날짜": "2024-08-29",
        "b-actin": 28.8218,
        "TIMP3": 28.0,
        "COL10A1": 38.0961,
        "FLG": 29.0278,
        "AQP3": 34.5933
    },
    {
        "이름": "도은주",
        "생년월일": "1982-04-21",
        "날짜": "2024-08-30",
        "b-actin": 31.2931,
        "TIMP3": 30.1368,
        "COL10A1": 31.3734,
        "FLG": 34.344,
        "AQP3": 32.5268
    },
    {
        "이름": "문성민",
        "생년월일": "2000-10-21",
        "날짜": "2024-08-30",
        "b-actin": 26.1972,
        "TIMP3": 24.0,
        "COL10A1": 27.9832,
        "FLG": 25.0077,
        "AQP3": 32.6173
    },
    {
        "이름": "김미연",
        "생년월일": "1993-12-15",
        "날짜": "2024-09-03",
        "b-actin": 25.0391,
        "TIMP3": 28.189,
        "COL10A1": 31.1732,
        "FLG": 27.2484,
        "AQP3": 26.6507
    },
    {
        "이름": "박석안",
        "생년월일": "1986-04-01",
        "날짜": "2024-09-03",
        "b-actin": 29.9212,
        "TIMP3": 28.8095,
        "COL10A1": 43.9673,
        "FLG": 33.8153,
        "AQP3": 58.2119
    },
    {
        "이름": "박세영",
        "생년월일": "1996-07-29",
        "날짜": "2024-09-04",
        "b-actin": 26.9813,
        "TIMP3": 30.0942,
        "COL10A1": 39.7806,
        "FLG": 26.6062,
        "AQP3": 26.7048
    },
    {
        "이름": "배상문",
        "생년월일": "1977-08-02",
        "날짜": "2024-09-04",
        "b-actin": 28.2236,
        "TIMP3": 32.1463,
        "COL10A1": 28.1855,
        "FLG": 30.4611,
        "AQP3": 60.2451
    }
]